[{"DISTRICT_ID":1353,"DISTRICT_CODE":"220901","DISTRICT_NAME":"นายายอาม   ","AMPHUR_ID":168,"PROVINCE_ID":13,"GEO_ID":5},{"DISTRICT_ID":1354,"DISTRICT_CODE":"220902","DISTRICT_NAME":"วังโตนด   ","AMPHUR_ID":168,"PROVINCE_ID":13,"GEO_ID":5},{"DISTRICT_ID":1355,"DISTRICT_CODE":"220903","DISTRICT_NAME":"กระแจะ   ","AMPHUR_ID":168,"PROVINCE_ID":13,"GEO_ID":5},{"DISTRICT_ID":1356,"DISTRICT_CODE":"220904","DISTRICT_NAME":"สนามไชย   ","AMPHUR_ID":168,"PROVINCE_ID":13,"GEO_ID":5},{"DISTRICT_ID":1357,"DISTRICT_CODE":"220905","DISTRICT_NAME":"ช้างข้าม   ","AMPHUR_ID":168,"PROVINCE_ID":13,"GEO_ID":5},{"DISTRICT_ID":1358,"DISTRICT_CODE":"220906","DISTRICT_NAME":"วังใหม่   ","AMPHUR_ID":168,"PROVINCE_ID":13,"GEO_ID":5}]
