[{"DISTRICT_ID":1399,"DISTRICT_CODE":"230501","DISTRICT_NAME":"แหลมงอบ   ","AMPHUR_ID":175,"PROVINCE_ID":14,"GEO_ID":5},{"DISTRICT_ID":1400,"DISTRICT_CODE":"230502","DISTRICT_NAME":"น้ำเชี่ยว   ","AMPHUR_ID":175,"PROVINCE_ID":14,"GEO_ID":5},{"DISTRICT_ID":1401,"DISTRICT_CODE":"230503","DISTRICT_NAME":"บางปิด   ","AMPHUR_ID":175,"PROVINCE_ID":14,"GEO_ID":5},{"DISTRICT_ID":1402,"DISTRICT_CODE":"230504","DISTRICT_NAME":"*เกาะช้าง   ","AMPHUR_ID":175,"PROVINCE_ID":14,"GEO_ID":5},{"DISTRICT_ID":1403,"DISTRICT_CODE":"230505","DISTRICT_NAME":"*เกาะหมาก   ","AMPHUR_ID":175,"PROVINCE_ID":14,"GEO_ID":5},{"DISTRICT_ID":1404,"DISTRICT_CODE":"230506","DISTRICT_NAME":"*เกาะกูด   ","AMPHUR_ID":175,"PROVINCE_ID":14,"GEO_ID":5},{"DISTRICT_ID":1405,"DISTRICT_CODE":"230507","DISTRICT_NAME":"คลองใหญ่   ","AMPHUR_ID":175,"PROVINCE_ID":14,"GEO_ID":5},{"DISTRICT_ID":1406,"DISTRICT_CODE":"230508","DISTRICT_NAME":"*เกาะช้างใต้   ","AMPHUR_ID":175,"PROVINCE_ID":14,"GEO_ID":5}]
