[{"DISTRICT_ID":2620,"DISTRICT_CODE":"330501","DISTRICT_NAME":"กันทรารมย์   ","AMPHUR_ID":294,"PROVINCE_ID":22,"GEO_ID":3},{"DISTRICT_ID":2621,"DISTRICT_CODE":"330502","DISTRICT_NAME":"จะกง   ","AMPHUR_ID":294,"PROVINCE_ID":22,"GEO_ID":3},{"DISTRICT_ID":2622,"DISTRICT_CODE":"330503","DISTRICT_NAME":"ใจดี   ","AMPHUR_ID":294,"PROVINCE_ID":22,"GEO_ID":3},{"DISTRICT_ID":2623,"DISTRICT_CODE":"330504","DISTRICT_NAME":"ดองกำเม็ด   ","AMPHUR_ID":294,"PROVINCE_ID":22,"GEO_ID":3},{"DISTRICT_ID":2624,"DISTRICT_CODE":"330505","DISTRICT_NAME":"โสน   ","AMPHUR_ID":294,"PROVINCE_ID":22,"GEO_ID":3},{"DISTRICT_ID":2625,"DISTRICT_CODE":"330506","DISTRICT_NAME":"ปรือใหญ่   ","AMPHUR_ID":294,"PROVINCE_ID":22,"GEO_ID":3},{"DISTRICT_ID":2626,"DISTRICT_CODE":"330507","DISTRICT_NAME":"สะเดาใหญ่   ","AMPHUR_ID":294,"PROVINCE_ID":22,"GEO_ID":3},{"DISTRICT_ID":2627,"DISTRICT_CODE":"330508","DISTRICT_NAME":"ตาอุด   ","AMPHUR_ID":294,"PROVINCE_ID":22,"GEO_ID":3},{"DISTRICT_ID":2628,"DISTRICT_CODE":"330509","DISTRICT_NAME":"ห้วยเหนือ   ","AMPHUR_ID":294,"PROVINCE_ID":22,"GEO_ID":3},{"DISTRICT_ID":2629,"DISTRICT_CODE":"330510","DISTRICT_NAME":"ห้วยใต้   ","AMPHUR_ID":294,"PROVINCE_ID":22,"GEO_ID":3},{"DISTRICT_ID":2630,"DISTRICT_CODE":"330511","DISTRICT_NAME":"หัวเสือ   ","AMPHUR_ID":294,"PROVINCE_ID":22,"GEO_ID":3},{"DISTRICT_ID":2631,"DISTRICT_CODE":"330512","DISTRICT_NAME":"*ละลม   ","AMPHUR_ID":294,"PROVINCE_ID":22,"GEO_ID":3},{"DISTRICT_ID":2632,"DISTRICT_CODE":"330513","DISTRICT_NAME":"ตะเคียน   ","AMPHUR_ID":294,"PROVINCE_ID":22,"GEO_ID":3},{"DISTRICT_ID":2633,"DISTRICT_CODE":"330514","DISTRICT_NAME":"*โคกตาล   ","AMPHUR_ID":294,"PROVINCE_ID":22,"GEO_ID":3},{"DISTRICT_ID":2634,"DISTRICT_CODE":"330515","DISTRICT_NAME":"นิคมพัฒนา   ","AMPHUR_ID":294,"PROVINCE_ID":22,"GEO_ID":3},{"DISTRICT_ID":2635,"DISTRICT_CODE":"330516","DISTRICT_NAME":"*ห้วยตามอญ   ","AMPHUR_ID":294,"PROVINCE_ID":22,"GEO_ID":3},{"DISTRICT_ID":2636,"DISTRICT_CODE":"330517","DISTRICT_NAME":"โคกเพชร   ","AMPHUR_ID":294,"PROVINCE_ID":22,"GEO_ID":3},{"DISTRICT_ID":2637,"DISTRICT_CODE":"330518","DISTRICT_NAME":"ปราสาท   ","AMPHUR_ID":294,"PROVINCE_ID":22,"GEO_ID":3},{"DISTRICT_ID":2638,"DISTRICT_CODE":"330519","DISTRICT_NAME":"*ตะเคียนราม   ","AMPHUR_ID":294,"PROVINCE_ID":22,"GEO_ID":3},{"DISTRICT_ID":2639,"DISTRICT_CODE":"330520","DISTRICT_NAME":"*ห้วยติ๊กชู   ","AMPHUR_ID":294,"PROVINCE_ID":22,"GEO_ID":3},{"DISTRICT_ID":2640,"DISTRICT_CODE":"330521","DISTRICT_NAME":"สำโรงตาเจ็น   ","AMPHUR_ID":294,"PROVINCE_ID":22,"GEO_ID":3},{"DISTRICT_ID":2641,"DISTRICT_CODE":"330522","DISTRICT_NAME":"ห้วยสำราญ   ","AMPHUR_ID":294,"PROVINCE_ID":22,"GEO_ID":3},{"DISTRICT_ID":2642,"DISTRICT_CODE":"330523","DISTRICT_NAME":"*ดงรัก   ","AMPHUR_ID":294,"PROVINCE_ID":22,"GEO_ID":3},{"DISTRICT_ID":2643,"DISTRICT_CODE":"330524","DISTRICT_NAME":"กฤษณา   ","AMPHUR_ID":294,"PROVINCE_ID":22,"GEO_ID":3},{"DISTRICT_ID":2644,"DISTRICT_CODE":"330525","DISTRICT_NAME":"ลมศักดิ์   ","AMPHUR_ID":294,"PROVINCE_ID":22,"GEO_ID":3},{"DISTRICT_ID":2645,"DISTRICT_CODE":"330526","DISTRICT_NAME":"หนองฉลอง   ","AMPHUR_ID":294,"PROVINCE_ID":22,"GEO_ID":3},{"DISTRICT_ID":2646,"DISTRICT_CODE":"330527","DISTRICT_NAME":"ศรีตระกูล   ","AMPHUR_ID":294,"PROVINCE_ID":22,"GEO_ID":3},{"DISTRICT_ID":2647,"DISTRICT_CODE":"330528","DISTRICT_NAME":"ศรีสะอาด   ","AMPHUR_ID":294,"PROVINCE_ID":22,"GEO_ID":3},{"DISTRICT_ID":2648,"DISTRICT_CODE":"330599","DISTRICT_NAME":"*ละลม   ","AMPHUR_ID":294,"PROVINCE_ID":22,"GEO_ID":3}]
