[{"DISTRICT_ID":2856,"DISTRICT_CODE":"340601","DISTRICT_NAME":"*ชานุมาน   ","AMPHUR_ID":317,"PROVINCE_ID":23,"GEO_ID":3},{"DISTRICT_ID":2857,"DISTRICT_CODE":"340602","DISTRICT_NAME":"*โคกสาร   ","AMPHUR_ID":317,"PROVINCE_ID":23,"GEO_ID":3},{"DISTRICT_ID":2858,"DISTRICT_CODE":"340603","DISTRICT_NAME":"*คำเขื่อนแก้ว   ","AMPHUR_ID":317,"PROVINCE_ID":23,"GEO_ID":3},{"DISTRICT_ID":2859,"DISTRICT_CODE":"340604","DISTRICT_NAME":"*หนองข่า   ","AMPHUR_ID":317,"PROVINCE_ID":23,"GEO_ID":3},{"DISTRICT_ID":2860,"DISTRICT_CODE":"340605","DISTRICT_NAME":"*คำโพน   ","AMPHUR_ID":317,"PROVINCE_ID":23,"GEO_ID":3},{"DISTRICT_ID":2861,"DISTRICT_CODE":"340606","DISTRICT_NAME":"*โคกก่ง   ","AMPHUR_ID":317,"PROVINCE_ID":23,"GEO_ID":3},{"DISTRICT_ID":2862,"DISTRICT_CODE":"340607","DISTRICT_NAME":"*ป่าก่อ   ","AMPHUR_ID":317,"PROVINCE_ID":23,"GEO_ID":3}]
