[{"DISTRICT_ID":4239,"DISTRICT_CODE":"431601","DISTRICT_NAME":"รัตนวาปี   ","AMPHUR_ID":475,"PROVINCE_ID":31,"GEO_ID":3},{"DISTRICT_ID":4240,"DISTRICT_CODE":"431602","DISTRICT_NAME":"นาทับไฮ   ","AMPHUR_ID":475,"PROVINCE_ID":31,"GEO_ID":3},{"DISTRICT_ID":4241,"DISTRICT_CODE":"431603","DISTRICT_NAME":"บ้านต้อน   ","AMPHUR_ID":475,"PROVINCE_ID":31,"GEO_ID":3},{"DISTRICT_ID":4242,"DISTRICT_CODE":"431604","DISTRICT_NAME":"พระบาทนาสิงห์   ","AMPHUR_ID":475,"PROVINCE_ID":31,"GEO_ID":3},{"DISTRICT_ID":4243,"DISTRICT_CODE":"431605","DISTRICT_NAME":"โพนแพง   ","AMPHUR_ID":475,"PROVINCE_ID":31,"GEO_ID":3}]
