[{"DISTRICT_ID":237,"DISTRICT_CODE":"110101","DISTRICT_NAME":"ปากน้ำ   ","AMPHUR_ID":52,"PROVINCE_ID":2,"GEO_ID":2},{"DISTRICT_ID":238,"DISTRICT_CODE":"110102","DISTRICT_NAME":"สำโรงเหนือ   ","AMPHUR_ID":52,"PROVINCE_ID":2,"GEO_ID":2},{"DISTRICT_ID":239,"DISTRICT_CODE":"110103","DISTRICT_NAME":"บางเมือง   ","AMPHUR_ID":52,"PROVINCE_ID":2,"GEO_ID":2},{"DISTRICT_ID":240,"DISTRICT_CODE":"110104","DISTRICT_NAME":"ท้ายบ้าน   ","AMPHUR_ID":52,"PROVINCE_ID":2,"GEO_ID":2},{"DISTRICT_ID":241,"DISTRICT_CODE":"110105","DISTRICT_NAME":"*นาเกลือ   ","AMPHUR_ID":52,"PROVINCE_ID":2,"GEO_ID":2},{"DISTRICT_ID":242,"DISTRICT_CODE":"110106","DISTRICT_NAME":"*แหลมฟ้าผ่า   ","AMPHUR_ID":52,"PROVINCE_ID":2,"GEO_ID":2},{"DISTRICT_ID":243,"DISTRICT_CODE":"110107","DISTRICT_NAME":"*ในคลองบางปลากด   ","AMPHUR_ID":52,"PROVINCE_ID":2,"GEO_ID":2},{"DISTRICT_ID":244,"DISTRICT_CODE":"110108","DISTRICT_NAME":"บางปูใหม่   ","AMPHUR_ID":52,"PROVINCE_ID":2,"GEO_ID":2},{"DISTRICT_ID":245,"DISTRICT_CODE":"110109","DISTRICT_NAME":"*ปากคลองบางปลากด   ","AMPHUR_ID":52,"PROVINCE_ID":2,"GEO_ID":2},{"DISTRICT_ID":246,"DISTRICT_CODE":"110110","DISTRICT_NAME":"แพรกษา   ","AMPHUR_ID":52,"PROVINCE_ID":2,"GEO_ID":2},{"DISTRICT_ID":247,"DISTRICT_CODE":"110111","DISTRICT_NAME":"บางโปรง   ","AMPHUR_ID":52,"PROVINCE_ID":2,"GEO_ID":2},{"DISTRICT_ID":248,"DISTRICT_CODE":"110112","DISTRICT_NAME":"บางปู   ","AMPHUR_ID":52,"PROVINCE_ID":2,"GEO_ID":2},{"DISTRICT_ID":249,"DISTRICT_CODE":"110113","DISTRICT_NAME":"บางด้วน   ","AMPHUR_ID":52,"PROVINCE_ID":2,"GEO_ID":2},{"DISTRICT_ID":250,"DISTRICT_CODE":"110114","DISTRICT_NAME":"บางเมืองใหม่   ","AMPHUR_ID":52,"PROVINCE_ID":2,"GEO_ID":2},{"DISTRICT_ID":251,"DISTRICT_CODE":"110115","DISTRICT_NAME":"เทพารักษ์   ","AMPHUR_ID":52,"PROVINCE_ID":2,"GEO_ID":2},{"DISTRICT_ID":252,"DISTRICT_CODE":"110116","DISTRICT_NAME":"ท้ายบ้านใหม่   ","AMPHUR_ID":52,"PROVINCE_ID":2,"GEO_ID":2},{"DISTRICT_ID":253,"DISTRICT_CODE":"110117","DISTRICT_NAME":"แพรกษาใหม่   ","AMPHUR_ID":52,"PROVINCE_ID":2,"GEO_ID":2},{"DISTRICT_ID":254,"DISTRICT_CODE":"110194","DISTRICT_NAME":"*บางปูเก่า   ","AMPHUR_ID":52,"PROVINCE_ID":2,"GEO_ID":2},{"DISTRICT_ID":255,"DISTRICT_CODE":"110195","DISTRICT_NAME":"*ในคลองบางปลากด   ","AMPHUR_ID":52,"PROVINCE_ID":2,"GEO_ID":2},{"DISTRICT_ID":256,"DISTRICT_CODE":"110196","DISTRICT_NAME":"*ปากคลองบางปลากด   ","AMPHUR_ID":52,"PROVINCE_ID":2,"GEO_ID":2},{"DISTRICT_ID":257,"DISTRICT_CODE":"110197","DISTRICT_NAME":"*แหลมฟ้าผ่า   ","AMPHUR_ID":52,"PROVINCE_ID":2,"GEO_ID":2},{"DISTRICT_ID":258,"DISTRICT_CODE":"110198","DISTRICT_NAME":"*บ้านคลองสวน   ","AMPHUR_ID":52,"PROVINCE_ID":2,"GEO_ID":2},{"DISTRICT_ID":259,"DISTRICT_CODE":"110199","DISTRICT_NAME":"*นาเกลือ   ","AMPHUR_ID":52,"PROVINCE_ID":2,"GEO_ID":2}]
