[{"DISTRICT_ID":5310,"DISTRICT_CODE":"501801","DISTRICT_NAME":"อมก๋อย   ","AMPHUR_ID":585,"PROVINCE_ID":38,"GEO_ID":1},{"DISTRICT_ID":5311,"DISTRICT_CODE":"501802","DISTRICT_NAME":"ยางเปียง   ","AMPHUR_ID":585,"PROVINCE_ID":38,"GEO_ID":1},{"DISTRICT_ID":5312,"DISTRICT_CODE":"501803","DISTRICT_NAME":"แม่ตื่น   ","AMPHUR_ID":585,"PROVINCE_ID":38,"GEO_ID":1},{"DISTRICT_ID":5313,"DISTRICT_CODE":"501804","DISTRICT_NAME":"ม่อนจอง   ","AMPHUR_ID":585,"PROVINCE_ID":38,"GEO_ID":1},{"DISTRICT_ID":5314,"DISTRICT_CODE":"501805","DISTRICT_NAME":"สบโขง   ","AMPHUR_ID":585,"PROVINCE_ID":38,"GEO_ID":1},{"DISTRICT_ID":5315,"DISTRICT_CODE":"501806","DISTRICT_NAME":"นาเกียน   ","AMPHUR_ID":585,"PROVINCE_ID":38,"GEO_ID":1}]
