[{"DISTRICT_ID":6009,"DISTRICT_CODE":"571201","DISTRICT_NAME":"แม่เปา   ","AMPHUR_ID":668,"PROVINCE_ID":45,"GEO_ID":1},{"DISTRICT_ID":6010,"DISTRICT_CODE":"571202","DISTRICT_NAME":"แม่ต๋ำ   ","AMPHUR_ID":668,"PROVINCE_ID":45,"GEO_ID":1},{"DISTRICT_ID":6011,"DISTRICT_CODE":"571203","DISTRICT_NAME":"ไม้ยา   ","AMPHUR_ID":668,"PROVINCE_ID":45,"GEO_ID":1},{"DISTRICT_ID":6012,"DISTRICT_CODE":"571204","DISTRICT_NAME":"เม็งราย   ","AMPHUR_ID":668,"PROVINCE_ID":45,"GEO_ID":1},{"DISTRICT_ID":6013,"DISTRICT_CODE":"571205","DISTRICT_NAME":"ตาดควัน   ","AMPHUR_ID":668,"PROVINCE_ID":45,"GEO_ID":1}]
