[{"DISTRICT_ID":5578,"DISTRICT_CODE":"530801","DISTRICT_NAME":"ศรีพนมมาศ   ","AMPHUR_ID":623,"PROVINCE_ID":41,"GEO_ID":1},{"DISTRICT_ID":5579,"DISTRICT_CODE":"530802","DISTRICT_NAME":"แม่พูล   ","AMPHUR_ID":623,"PROVINCE_ID":41,"GEO_ID":1},{"DISTRICT_ID":5580,"DISTRICT_CODE":"530803","DISTRICT_NAME":"นานกกก   ","AMPHUR_ID":623,"PROVINCE_ID":41,"GEO_ID":1},{"DISTRICT_ID":5581,"DISTRICT_CODE":"530804","DISTRICT_NAME":"ฝายหลวง   ","AMPHUR_ID":623,"PROVINCE_ID":41,"GEO_ID":1},{"DISTRICT_ID":5582,"DISTRICT_CODE":"530805","DISTRICT_NAME":"ชัยจุมพล   ","AMPHUR_ID":623,"PROVINCE_ID":41,"GEO_ID":1},{"DISTRICT_ID":5583,"DISTRICT_CODE":"530806","DISTRICT_NAME":"ไผ่ล้อม   ","AMPHUR_ID":623,"PROVINCE_ID":41,"GEO_ID":1},{"DISTRICT_ID":5584,"DISTRICT_CODE":"530807","DISTRICT_NAME":"ทุ่งยั้ง   ","AMPHUR_ID":623,"PROVINCE_ID":41,"GEO_ID":1},{"DISTRICT_ID":5585,"DISTRICT_CODE":"530808","DISTRICT_NAME":"ด่านแม่คำมัน   ","AMPHUR_ID":623,"PROVINCE_ID":41,"GEO_ID":1},{"DISTRICT_ID":5586,"DISTRICT_CODE":"530899","DISTRICT_NAME":"*ศรีพนมมาศ   ","AMPHUR_ID":623,"PROVINCE_ID":41,"GEO_ID":1}]
