[{"DISTRICT_ID":8153,"DISTRICT_CODE":"860701","DISTRICT_NAME":"นาโพธิ์   ","AMPHUR_ID":916,"PROVINCE_ID":69,"GEO_ID":6},{"DISTRICT_ID":8154,"DISTRICT_CODE":"860702","DISTRICT_NAME":"สวี   ","AMPHUR_ID":916,"PROVINCE_ID":69,"GEO_ID":6},{"DISTRICT_ID":8155,"DISTRICT_CODE":"860703","DISTRICT_NAME":"ทุ่งระยะ   ","AMPHUR_ID":916,"PROVINCE_ID":69,"GEO_ID":6},{"DISTRICT_ID":8156,"DISTRICT_CODE":"860704","DISTRICT_NAME":"ท่าหิน   ","AMPHUR_ID":916,"PROVINCE_ID":69,"GEO_ID":6},{"DISTRICT_ID":8157,"DISTRICT_CODE":"860705","DISTRICT_NAME":"ปากแพรก   ","AMPHUR_ID":916,"PROVINCE_ID":69,"GEO_ID":6},{"DISTRICT_ID":8158,"DISTRICT_CODE":"860706","DISTRICT_NAME":"ด่านสวี   ","AMPHUR_ID":916,"PROVINCE_ID":69,"GEO_ID":6},{"DISTRICT_ID":8159,"DISTRICT_CODE":"860707","DISTRICT_NAME":"ครน   ","AMPHUR_ID":916,"PROVINCE_ID":69,"GEO_ID":6},{"DISTRICT_ID":8160,"DISTRICT_CODE":"860708","DISTRICT_NAME":"วิสัยใต้   ","AMPHUR_ID":916,"PROVINCE_ID":69,"GEO_ID":6},{"DISTRICT_ID":8161,"DISTRICT_CODE":"860709","DISTRICT_NAME":"นาสัก   ","AMPHUR_ID":916,"PROVINCE_ID":69,"GEO_ID":6},{"DISTRICT_ID":8162,"DISTRICT_CODE":"860710","DISTRICT_NAME":"เขาทะลุ   ","AMPHUR_ID":916,"PROVINCE_ID":69,"GEO_ID":6},{"DISTRICT_ID":8163,"DISTRICT_CODE":"860711","DISTRICT_NAME":"เขาค่าย   ","AMPHUR_ID":916,"PROVINCE_ID":69,"GEO_ID":6}]
