[{"DISTRICT_ID":8347,"DISTRICT_CODE":"910101","DISTRICT_NAME":"พิมาน   ","AMPHUR_ID":936,"PROVINCE_ID":71,"GEO_ID":6},{"DISTRICT_ID":8348,"DISTRICT_CODE":"910102","DISTRICT_NAME":"คลองขุด   ","AMPHUR_ID":936,"PROVINCE_ID":71,"GEO_ID":6},{"DISTRICT_ID":8349,"DISTRICT_CODE":"910103","DISTRICT_NAME":"ควนขัน   ","AMPHUR_ID":936,"PROVINCE_ID":71,"GEO_ID":6},{"DISTRICT_ID":8350,"DISTRICT_CODE":"910104","DISTRICT_NAME":"บ้านควน   ","AMPHUR_ID":936,"PROVINCE_ID":71,"GEO_ID":6},{"DISTRICT_ID":8351,"DISTRICT_CODE":"910105","DISTRICT_NAME":"ฉลุง   ","AMPHUR_ID":936,"PROVINCE_ID":71,"GEO_ID":6},{"DISTRICT_ID":8352,"DISTRICT_CODE":"910106","DISTRICT_NAME":"เกาะสาหร่าย   ","AMPHUR_ID":936,"PROVINCE_ID":71,"GEO_ID":6},{"DISTRICT_ID":8353,"DISTRICT_CODE":"910107","DISTRICT_NAME":"ตันหยงโป   ","AMPHUR_ID":936,"PROVINCE_ID":71,"GEO_ID":6},{"DISTRICT_ID":8354,"DISTRICT_CODE":"910108","DISTRICT_NAME":"เจ๊ะบิลัง   ","AMPHUR_ID":936,"PROVINCE_ID":71,"GEO_ID":6},{"DISTRICT_ID":8355,"DISTRICT_CODE":"910109","DISTRICT_NAME":"ตำมะลัง   ","AMPHUR_ID":936,"PROVINCE_ID":71,"GEO_ID":6},{"DISTRICT_ID":8356,"DISTRICT_CODE":"910110","DISTRICT_NAME":"ปูยู   ","AMPHUR_ID":936,"PROVINCE_ID":71,"GEO_ID":6},{"DISTRICT_ID":8357,"DISTRICT_CODE":"910111","DISTRICT_NAME":"ควนโพธิ์   ","AMPHUR_ID":936,"PROVINCE_ID":71,"GEO_ID":6},{"DISTRICT_ID":8358,"DISTRICT_CODE":"910112","DISTRICT_NAME":"เกตรี   ","AMPHUR_ID":936,"PROVINCE_ID":71,"GEO_ID":6},{"DISTRICT_ID":8359,"DISTRICT_CODE":"910199","DISTRICT_NAME":"*ท่าแพ   ","AMPHUR_ID":936,"PROVINCE_ID":71,"GEO_ID":6}]
